MissingValuesGraph/MissValues.py
MissingValuesGraph/__init__.py
MissingValuesGraph-4.0.0.dist-info/METADATA
MissingValuesGraph-4.0.0.dist-info/WHEEL
MissingValuesGraph-4.0.0.dist-info/top_level.txt
MissingValuesGraph-4.0.0.dist-info/RECORD
