Metadata-Version: 2.1
Name: MissingValuesGraph
Version: 4.0.0
Summary: Find the missing values for any dataframe/dataset
Home-page: https://github.com/sthirumoorthi/MissingValuesGraph
Author: Thirumoorthi S
Author-email: thirumoorthiksr@gmail.com
License: UNKNOWN
Platform: UNKNOWN
Classifier: Programming Language :: Python
Classifier: Programming Language :: Python :: 3
